{
	"$id": "controllable.schema.json",
	"$schema": "https://json-schema.org/draft-07/schema",

	"title": "Controllable Component",
	"description": "Schema validating the Controllable component.",

	"examples" : [
		{"type" : "controllable:Controllable", "params" :  {"key_profile" : "KEY_CONTROLS_1"}},
		{
			"type" : "controllable:Controllable", 
			"params" :  {
				"key_profile" : "KEY_CONTROLS_1",
				"control_keys" : {
					"LEFT" : 276, 
					"RIGHT": 275, 
					"UP": 273, 
					"DOWN" : 274, 
					"ATTACK" : 122
				},
				"control_cmds" : {
					"LEFT" : [["move", {"direction" : "left"}]],
					"RIGHT": [["move", {"direction" : "right"}]],
					"UP" : [["move", {"direction" : "up"}]],
					"DOWN" : [["move", {"direction" : "down"}]],
					"ATTACK" : [["attack", {}]]}
			}
		}
	],

	"required": [ "type", "params"],
	"properties": {
		"type": {
			"description" : "Path to the component class.",
			"enum": [ "controllable:Controllable" ]
		},
		"params": {
			"title": "Component parameters",
			"description" : "Parameters of the Controllable component class - 'key_profile', 'control_keys', 'control_cmds'.",
			"type": "object",
			"$ref": "#/$defs/cond_params",
			"properties": {
				"key_profile" : {
					"title": "Keys Layout",
					"description": "Layout of control keys.",
					"type": "string",
					"oneOf":[
						{"pattern": "^KEY_CONTROLS*"},
						{"enum": ["DEFAULT"]}
					],
					"default": "default"
				},
				"control_keys" : {
					"title": "Control Keys",
					"description": "Keys assigned to actions.",
					"type": "object",
					"required": ["LEFT", "RIGHT", "UP", "DOWN", "ATTACK"]
				},
				"control_cmds" : {
					"title": "Control Commands",
					"description": "List of commands assigned to actions.",
					"type": "object",
					"required": ["LEFT", "RIGHT", "UP", "DOWN", "ATTACK"],
					"properties": {
						"left": {"type": "array", "items": {"$ref": "../command.schema.json"}},
						"right": {"type": "array", "items": {"$ref": "../command.schema.json"}},
						"up": {"type": "array", "items": {"$ref": "../command.schema.json"}},
						"down": {"type": "array", "items": {"$ref": "../command.schema.json"}},
						"attack": {"type": "array", "items": {"$ref": "../command.schema.json"}}
					}
				}
			}
		}
	},

	"$defs" : {
		"cond_params": {
			"description" : "Conditions for 'param' properties.",
			"anyOf": [true]
		}
	}
	
}