{
	"$id": "sound_fx_on_creation.schema.json",
	"$schema": "https://json-schema.org/draft-07/schema",

	"title": "SoundFXOnCreation Component",
	"description": "Schema validating the SoundFXOnCreation component.",

	"examples" : [
		{"type" : "sound_fx_on_creation:SoundFXOnCreation", "params" : {"sound" : "ouch.mp3"}}
	],

	"required": [ "type", "params"],
	"properties": {
		"type": {
			"description" : "Path to the component class.",
			"enum": [ "sound_fx_on_creation:SoundFXOnCreation" ]
		},
		"params": {
			"title": "Component parameters",
			"description" : "Parameters of the SoundFXOnCreation component class - 'sound'.",
			"type": "object",
			"$ref": "#/$defs/cond_params",
			"required": ["sound"],
			"properties": {
				"sound" : {
					"$ref": "../definitions.schema.json#/definitions/sound_file"
				}
			}
		}
	},

	"$defs" : {
		"cond_params": {
			"description" : "Conditions for 'param' properties.",
			"anyOf": [true]
		}
	}
	
}